__init__.py
downloader.py
markdown_image_downloader-0.1.7.dist-info/licenses/LICENSE
markdown_image_downloader-0.1.7.dist-info/METADATA
markdown_image_downloader-0.1.7.dist-info/WHEEL
markdown_image_downloader-0.1.7.dist-info/entry_points.txt
markdown_image_downloader-0.1.7.dist-info/top_level.txt
markdown_image_downloader-0.1.7.dist-info/RECORD
