Metadata-Version: 2.4
Name: markdown-image-downloader
Version: 0.1.7
Summary: A tool to download and organize images referenced in markdown files
Author-email: mufidu <mufidu@outlook.com>
License: The MIT License (MIT)
Project-URL: Homepage, https://github.com/mufidu/markdown-image-downloader
Project-URL: Source, https://github.com/mufidu/markdown-image-downloader.git
Keywords: markdown,image,downloader,automation
Classifier: License :: OSI Approved :: MIT License
Classifier: Programming Language :: Python
Requires-Python: >=3.9
License-File: LICENSE
Requires-Dist: pillow>=11.0.0
Requires-Dist: tqdm>=4.66.5
Dynamic: license-file
